low_index/__init__.py
low_index/test.py
low_index/_low_index.cpython-312-aarch64-linux-gnu.so
low_index/benchmark.py
low_index/benchmark_util.py
low_index-1.2.1.dist-info/RECORD
low_index-1.2.1.dist-info/top_level.txt
low_index-1.2.1.dist-info/WHEEL
low_index-1.2.1.dist-info/METADATA
