Metadata-Version: 2.1
Name: low_index
Version: 1.2.1
Summary: Enumerates low index subgroups of a finitely presented group
Author-email: Marc Culler <culler@marc-culler.info>, "Nathan M. Dunfield" <nathan@dunfield.info>, Matthias Goerner <enischte@gmail.com>
Project-URL: Homepage, https://github.com/3-manifolds/low_index
Classifier: Development Status :: 5 - Production/Stable
Classifier: Intended Audience :: Science/Research
Classifier: License :: OSI Approved :: GNU General Public License v2 or later (GPLv2+)
Classifier: Operating System :: OS Independent
Classifier: Programming Language :: C++
Classifier: Programming Language :: Python
Classifier: Topic :: Scientific/Engineering :: Mathematics
Requires-Python: >=3.8
